{
	"poki_template_version": 1,
	"extra_html": {
	  "head": [
		"<!-- will be copied to the resulting head //-->"
	  ],
	  "body": [
		"<!-- will be copied to the resulting body //-->",
		"<!-- will also be copied to the resulting body //-->"
	  ]
	},
	"background_color": "#231F20",
	"background_filename": "",
	"code_filename": "0d40b75df604cb1a60a726c4914ed74a.wasm",
	"company_name": "Blabbers",
	"data_filename": "5f746f30239e18900898913822d462c8.data",
	"decompression_fallback": "Disabled",
	"development_player": "false",
	"framework_filename": "296c721bb4886ce39fe005e3c282046c.js",
	"height": "600",
	"loader_filename": "fish-rescue.loader.js",
	"memory_filename": "",
	"product_name": "fish-rescue",
	"product_version": "0.1",
	"splash_screen_style": "Dark",
	"symbols_filename": "",
	"unity_version": "2022.3.18f1",
	"use_data_caching": "true",
	"use_threads": "false",
	"use_wasm": "true",
	"use_webgl_1_0": "false",
	"use_webgl_2_0": "true",
	"width": "960"
  }
